mountepy/__init__.py
mountepy/http_service.py
mountepy/mb_mgmt.py
mountepy/mountebank.py
mountepy-0.4.1.dist-info/DESCRIPTION.rst
mountepy-0.4.1.dist-info/METADATA
mountepy-0.4.1.dist-info/RECORD
mountepy-0.4.1.dist-info/WHEEL
mountepy-0.4.1.dist-info/metadata.json
mountepy-0.4.1.dist-info/top_level.txt
