Metadata-Version: 2.0
Name: mountepy
Version: 0.4.1
Summary: Utilities for creating (micro)service tests. Based on Mountebank.
Home-page: https://github.com/butla/mountepy
Author: Michał Bultrowicz
Author-email: michal.bultrowicz@gmail.com
License: BSD Zero Clause
Keywords: test http mountebank microservice
Platform: UNKNOWN
Classifier: Programming Language :: Python :: 3.4
Classifier: Operating System :: POSIX :: Linux
Classifier: Development Status :: 4 - Beta
Classifier: License :: Freely Distributable
Classifier: Intended Audience :: Developers
Classifier: Natural Language :: English
Requires-Dist: port-for
Requires-Dist: python-dateutil
Requires-Dist: requests
